napari_spatial_omics/__init__.py
napari_spatial_omics/_csv_io.py
napari_spatial_omics/_dock_widget_original.py
napari_spatial_omics/_function.py
napari_spatial_omics/_reader.py
napari_spatial_omics/_reader_function.py
napari_spatial_omics/_tests/__init__.py
napari_spatial_omics/_tests/test_function.py
napari_spatial_omics-0.0.8.dist-info/LICENSE
napari_spatial_omics-0.0.8.dist-info/METADATA
napari_spatial_omics-0.0.8.dist-info/WHEEL
napari_spatial_omics-0.0.8.dist-info/entry_points.txt
napari_spatial_omics-0.0.8.dist-info/top_level.txt
napari_spatial_omics-0.0.8.dist-info/RECORD
