Metadata-Version: 2.1
Name: napari-spatial-omics
Version: 0.0.8
Summary: A simple plugin to visualize spatial omic data stored in CSV format
Home-page: https://github.com/sebgoti/napari-spatial-omics
Author: Sebastian Gonzalez-Tirado
Author-email: sebgoti8@gmail.com
License: BSD-3-Clause
Project-URL: Bug Tracker, https://github.com/sebgoti/napari-spatial-omics/issues
Project-URL: Documentation, https://github.com/sebgoti/napari-spatial-omics#README.md
Project-URL: Source Code, https://github.com/sebgoti/napari-spatial-omics
Project-URL: User Support, https://github.com/sebgoti/napari-spatial-omics/issues
Platform: UNKNOWN
Classifier: Development Status :: 2 - Pre-Alpha
Classifier: Intended Audience :: Developers
Classifier: Framework :: napari
Classifier: Topic :: Software Development :: Testing
Classifier: Programming Language :: Python
Classifier: Programming Language :: Python :: 3
Classifier: Programming Language :: Python :: 3.7
Classifier: Programming Language :: Python :: 3.8
Classifier: Programming Language :: Python :: 3.9
Classifier: Operating System :: OS Independent
Classifier: License :: OSI Approved :: BSD License
Requires-Python: >=3.7
License-File: LICENSE
Requires-Dist: napari-plugin-engine (>=0.1.4)
Requires-Dist: numpy
Requires-Dist: pandas
